hpi_feed-0.1.1.dist-info/licenses/LICENSE
my_feed/__init__.pyi
my_feed/__main__.py
my_feed/blur.py
my_feed/log.py
my_feed/py.typed
my_feed/timeshift.py
my_feed/transform.py
my_feed/sources/__init__.pyi
my_feed/sources/common.py
my_feed/sources/facebook_spotify_listens.py
my_feed/sources/games.py
my_feed/sources/listens.py
my_feed/sources/mal.py
my_feed/sources/model.py
my_feed/sources/mpv.py
my_feed/sources/nextalbums.py
my_feed/sources/offline_listens.py
my_feed/sources/trakt/__init__.py
my_feed/sources/trakt/tmdb.py
hpi_feed-0.1.1.dist-info/METADATA
hpi_feed-0.1.1.dist-info/WHEEL
hpi_feed-0.1.1.dist-info/entry_points.txt
hpi_feed-0.1.1.dist-info/top_level.txt
hpi_feed-0.1.1.dist-info/RECORD
