Metadata-Version: 2.4
Name: hpi_feed
Version: 0.1.1
Summary: A personal feed/website
Author: purarue
License-Expression: MIT
Project-URL: Homepage, https://github.com/purarue/my_feed
Classifier: Programming Language :: Python :: 3
Classifier: Programming Language :: Python :: 3 :: Only
Classifier: Programming Language :: Python :: 3.10
Classifier: Programming Language :: Python :: 3.11
Classifier: Programming Language :: Python :: 3.12
Classifier: Programming Language :: Python :: 3.13
Classifier: Programming Language :: Python :: 3.14
Requires-Python: >=3.10
License-File: LICENSE
Requires-Dist: arrow
Requires-Dist: chess
Requires-Dist: logzero
Requires-Dist: mutagen
Requires-Dist: url-cache
Dynamic: license-file
